nonebot_plugin_picsearcher/__init__.py
nonebot_plugin_picsearcher/ascii2d.py
nonebot_plugin_picsearcher/ex.py
nonebot_plugin_picsearcher/formdata.py
nonebot_plugin_picsearcher/iqdb.py
nonebot_plugin_picsearcher/proxy.py
nonebot_plugin_picsearcher/saucenao.py
nonebot_plugin_picsearcher/trace.py
nonebot_plugin_picsearcher/utils.py
nonebot_plugin_picsearcher/yandex.py
nonebot_plugin_picsearcher-0.1.10.dist-info/LICENSE
nonebot_plugin_picsearcher-0.1.10.dist-info/METADATA
nonebot_plugin_picsearcher-0.1.10.dist-info/WHEEL
nonebot_plugin_picsearcher-0.1.10.dist-info/top_level.txt
nonebot_plugin_picsearcher-0.1.10.dist-info/RECORD
