Metadata-Version: 2.1
Name: nonebot-plugin-picsearcher
Version: 0.1.10
Summary: A picsearch plugin for nonebot2
Home-page: https://github.com/synodriver/nonebot_plugin_picsearcher
Author: synodriver
Author-email: diguohuangjiajinweijun@gmail.com
License: GPLv3
Project-URL: Bug Tracker, https://github.com/synodriver/nonebot_plugin_picsearcher/issues
Keywords: nonebot
Classifier: Framework :: AsyncIO
Classifier: Operating System :: OS Independent
Classifier: License :: OSI Approved :: GNU General Public License v3 (GPLv3)
Classifier: Programming Language :: Python
Classifier: Programming Language :: Python :: 3.7
Classifier: Programming Language :: Python :: 3.8
Classifier: Programming Language :: Python :: 3.9
Classifier: Programming Language :: Python :: 3.10
Classifier: Programming Language :: Python :: Implementation :: CPython
Requires-Python: >=3.7
License-File: LICENSE
